matcher.py
websockets_router-0.1.6.data/scripts/matcher.py
websockets_router-0.1.6.dist-info/AUTHORS
websockets_router-0.1.6.dist-info/LICENSE
websockets_router-0.1.6.dist-info/METADATA
websockets_router-0.1.6.dist-info/WHEEL
websockets_router-0.1.6.dist-info/top_level.txt
websockets_router-0.1.6.dist-info/RECORD
